xdgmenu.py
xdgmenu-0.0.0.dist-info/DESCRIPTION.rst
xdgmenu-0.0.0.dist-info/METADATA
xdgmenu-0.0.0.dist-info/RECORD
xdgmenu-0.0.0.dist-info/WHEEL
xdgmenu-0.0.0.dist-info/entry_points.txt
xdgmenu-0.0.0.dist-info/metadata.json
xdgmenu-0.0.0.dist-info/top_level.txt
