Metadata-Version: 2.0
Name: xdgmenu
Version: 0.0.0
Summary: A simple freedesktop based Applications menu using ncurses
Home-page: https://github.com/crichon/xdgmenu
Author: crichon
Author-email: richon.c@gmail.com
License: MIT
Keywords: ncurses freedesktop application_launcher
Platform: UNKNOWN
Classifier: Development Status :: 3 - Alpha
Classifier: Intended Audience :: End Users/Desktop
Classifier: Topic :: Utilities
Classifier: License :: OSI Approved :: MIT License
Classifier: Programming Language :: Python :: 2
Classifier: Programming Language :: Python :: 2.7
Classifier: Programming Language :: Python :: 3
Classifier: Programming Language :: Python :: 3.3
Classifier: Programming Language :: Python :: 3.4
Classifier: Programming Language :: Python :: 3.5
Requires-Dist: pyxdg
Requires-Dist: urwid
Provides-Extra: dev
Requires-Dist: check-manifest; extra == 'dev'
Requires-Dist: pylint; extra == 'dev'
